{
    "universal": false,
    "flips": ["zoom_y"],
    "keymaps": [
        {
            "keymaps": ["3D View", "Font", "Vertex Paint", "Weight Paint", "Image Paint", "Sculpt", "Particle"],
            "value_type": "Left Mouse",
            "input_settings": {
                "allowed_transitions": ["NONE:ORBIT", "ORBIT:FLY", "ORBIT:FPS", "FLY:FPS"],
                "zbrush_mode": true,
                "independent_modes": true,
                "keys_orbit_snap": "Shift",
                "keys_pan": "Alt",
                "keys_zoom": "!Alt"
            }
        },
        {
            "keymaps": ["3D View", "Font", "Vertex Paint", "Weight Paint", "Image Paint", "Sculpt", "Particle"],
            "value_type": "Left Mouse",
            "alt": true,
            "input_settings": {
                "allowed_transitions": ["NONE:PAN", "PAN:ZOOM"],
                "zbrush_mode": true,
                "independent_modes": true,
                "keys_orbit_snap": "Shift",
                "keys_pan": "Alt",
                "keys_zoom": "!Alt"
            }
        }
    ]
}