{"manuellab_version": [1, 2, 0], "proportions": {"waist-girth": 0.4419, "feet-length": 0.1539, "shoulders-width": 0.1843, "upperleg-bottom-girth": 0.2283, "approximate-height_Z": 1.0, "neck-height_Z": 0.0333, "lowerleg-bottom-girth": 0.1239, "wrist-girth": 0.0846, "neck-girth": 0.2208, "upperleg-length": 0.2202, "torso-height_Z": 0.2258, "lowerleg-calf-girth": 0.2318, "hands-length": 0.1104, "chest-girth": 0.5798, "buttock-width_X": 0.1879, "chest-width_X": 0.2061, "upperarm-axillary-girth": 0.221, "head-width_X": 0.0814, "upperarm-length": 0.1764, "lowerleg-length": 0.2204, "head-length": 0.1147, "buttock-depth_Y": 0.1308, "feet-height_Z": 0.0478, "forearm-length": 0.1741, "feet-width": 0.0613, "head-height_Z": 0.127, "chest-depth_Y": 0.1601, "upperleg-top-girth": 0.3155, "hands-width": 0.0449, "elbow-girth": 0.1741, "buttock-height_Z": 0.1369, "buttock-girth": 0.5099, "feet-heel-width": 0.0348}, "structural": {"Torso_Tone": 0.8, "Neck_Tone": 0.71, "Pelvis_GluteusMass": 0.82, "Pelvis_GluteusTone": 0.65, "Torso_SizeY": 0.71, "Neck_Collarbone": 0.8, "Waist_Size": 0.41, "Torso_Dorsi": 0.65, "Shoulders_Mass": 0.59, "Arms_UpperarmTone": 0.68, "Legs_LowerlegsTone": 0.8, "Shoulders_PosZ": 0.56, "Legs_UpperlegInCurve": 0.26, "Legs_LowerlegsMass": 0.59, "Arms_ForearmTone": 0.77, "Legs_UpperlegsTone": 0.71, "Arms_UpperarmMass": 0.59}}