{"proportions": {"hands_width": 0.0429, "feet_heel_width": 0.0417, "forearm_length": 0.1707, "chest_width_X": 0.139, "lowerleg_bottom_girth": 0.1182, "buttock_girth": 0.5143, "shoulders_width": 0.1514, "elbow_girth": 0.163, "feet_height_Z": 0.0472, "upperarm_length": 0.1617, "head_length": 0.1097, "head_height_Z": 0.1214, "buttock_height_Z": 0.1208, "feet_width": 0.0587, "chest_depth_Y": 0.1261, "lowerleg_length": 0.2223, "upperarm_axillary_girth": 0.1756, "upperleg_length": 0.2401, "upperleg_top_girth": 0.2928, "head_width_X": 0.0779, "lowerleg_calf_girth": 0.2168, "wrist_girth": 0.081, "feet_length": 0.1472, "hands_length": 0.1056, "waist_girth": 0.4063, "upperleg_bottom_girth": 0.2122, "buttock_width_X": 0.1912, "buttock_depth_Y": 0.1294, "body_height_Z": 1.0, "chest_girth": 0.4445, "torso_height_Z": 0.2208, "neck_girth": 0.2008, "neck_height_Z": 0.037}, "manuellab_version": [1, 2, 0], "structural": {"Arms_UpperarmMass": 0.26, "Arms_ForearmTone": 0.8, "Pelvis_GluteusSize": 0.68, "Legs_LowerlegsTone": 0.85, "Torso_Mass": 0.14, "Arms_UpperarmTone": 1.0, "Legs_UpperlegLength": 0.71, "Arms_UpperarmLength": 0.65, "Torso_SizeX": 0.32, "Legs_LowerlegLength": 0.62, "Torso_Vshape": 0.12, "Torso_Tone": 1.0, "Shoulders_Mass": 0.08}}
