{"manuellab_version": [1, 2, 0], "proportions": {"waist_girth": 0.4499, "feet_length": 0.1562, "shoulders_width": 0.1444, "upperleg_bottom_girth": 0.224, "body_height_Z": 1.0, "neck_height_Z": 0.0362, "lowerleg_bottom_girth": 0.126, "wrist_girth": 0.0854, "neck_girth": 0.2172, "upperleg_length": 0.2118, "torso_height_Z": 0.2255, "lowerleg_calf_girth": 0.2162, "hands_length": 0.1121, "chest_girth": 0.4858, "buttock_width_X": 0.1904, "chest_width_X": 0.1541, "upperarm_axillary_girth": 0.196, "head_width_X": 0.0857, "upperarm_length": 0.1689, "lowerleg_length": 0.2166, "head_length": 0.1207, "buttock_depth_Y": 0.1338, "feet_height_Z": 0.0486, "forearm_length": 0.1794, "feet_width": 0.0623, "head_height_Z": 0.1335, "chest_depth_Y": 0.1364, "upperleg_top_girth": 0.3095, "hands_width": 0.0456, "elbow_girth": 0.1576, "buttock_height_Z": 0.1398, "buttock_girth": 0.5147, "feet_heel_width": 0.0353}, "structural": {"Legs_LowerlegLength": 0.39, "Torso_Vshape": 0.0, "Legs_UpperlegLength": 0.32, "Head_Size": 0.59}}
